README.rst
setup.py
CSharpCCF/__init__.py
CSharpCCF/__main__.py
CSharpCCF/lexer.py
CSharpCCF/main.py
CSharpCCF/static_analyzer.py
CSharpCCF.egg-info/PKG-INFO
CSharpCCF.egg-info/SOURCES.txt
CSharpCCF.egg-info/dependency_links.txt
CSharpCCF.egg-info/entry_points.txt
CSharpCCF.egg-info/top_level.txt