Metadata-Version: 1.0
Name: CSharpCCF
Version: 0.3.1
Summary: C# CCF
Home-page: https://pypi.org/user/MariKush/
Author: Mariia Kushnirenko
Author-email: kms1999@ukr.net
License: UNKNOWN
Platform: UNKNOWN
